SG.py
sendgridsend-0.1.3.dist-info/METADATA
sendgridsend-0.1.3.dist-info/WHEEL
sendgridsend-0.1.3.dist-info/entry_points.txt
sendgridsend-0.1.3.dist-info/RECORD
